adam_credmanager/__init__.py
adam_credmanager/adam_credmanager.py
adam_credmanager-0.1.5.dist-info/METADATA
adam_credmanager-0.1.5.dist-info/WHEEL
adam_credmanager-0.1.5.dist-info/RECORD
