Metadata-Version: 2.1
Name: adam-credmanager
Version: 0.1.5
Summary: 
Author: Eduardo Pagnone
Author-email: eduardopagnone@gmail.com
Classifier: Programming Language :: Python :: 2
Classifier: Programming Language :: Python :: 2.7
Classifier: Programming Language :: Python :: 3
Classifier: Programming Language :: Python :: 3.4
Classifier: Programming Language :: Python :: 3.5
Classifier: Programming Language :: Python :: 3.6
Classifier: Programming Language :: Python :: 3.7
Classifier: Programming Language :: Python :: 3.8
Classifier: Programming Language :: Python :: 3.9
Classifier: Programming Language :: Python :: 3.10
Classifier: Programming Language :: Python :: 3.11
Requires-Dist: google-cloud-resource-manager (>=1.10.1,<2.0.0)
Requires-Dist: google-cloud-secret-manager (>=2.16.1,<3.0.0)
